circuits/__init__.py
circuits/apps.py
circuits/choices.py
circuits/filtersets.py
circuits/signals.py
circuits/urls.py
circuits/views.py
circuits/api/__init__.py
circuits/api/nested_serializers.py
circuits/api/serializers.py
circuits/api/urls.py
circuits/api/views.py
circuits/forms/__init__.py
circuits/forms/bulk_edit.py
circuits/forms/bulk_import.py
circuits/forms/filtersets.py
circuits/forms/models.py
circuits/graphql/__init__.py
circuits/graphql/schema.py
circuits/graphql/types.py
circuits/migrations/0001_squashed.py
circuits/migrations/0002_squashed_0029.py
circuits/migrations/0003_extend_tag_support.py
circuits/migrations/0004_rename_cable_peer.py
circuits/migrations/0032_provider_service_id.py
circuits/migrations/0033_standardize_id_fields.py
circuits/migrations/0034_created_datetimefield.py
circuits/migrations/0035_provider_asns.py
circuits/migrations/__init__.py
circuits/models/__init__.py
circuits/models/circuits.py
circuits/models/providers.py
circuits/tables/__init__.py
circuits/tables/circuits.py
circuits/tables/columns.py
circuits/tables/providers.py
circuits/tests/__init__.py
circuits/tests/test_api.py
circuits/tests/test_filtersets.py
circuits/tests/test_views.py
dcim/__init__.py
dcim/apps.py
dcim/choices.py
dcim/constants.py
dcim/fields.py
dcim/filtersets.py
dcim/lookups.py
dcim/signals.py
dcim/svg.py
dcim/urls.py
dcim/utils.py
dcim/views.py
dcim/api/__init__.py
dcim/api/exceptions.py
dcim/api/nested_serializers.py
dcim/api/serializers.py
dcim/api/urls.py
dcim/api/views.py
dcim/forms/__init__.py
dcim/forms/bulk_create.py
dcim/forms/bulk_edit.py
dcim/forms/bulk_import.py
dcim/forms/common.py
dcim/forms/connections.py
dcim/forms/filtersets.py
dcim/forms/formsets.py
dcim/forms/models.py
dcim/forms/object_create.py
dcim/forms/object_import.py
dcim/graphql/__init__.py
dcim/graphql/schema.py
dcim/graphql/types.py
dcim/management/__init__.py
dcim/management/commands/__init__.py
dcim/management/commands/trace_paths.py
dcim/migrations/0001_squashed.py
netbox_pip-0.0.10.dist-info/METADATA
netbox_pip-0.0.10.dist-info/WHEEL
netbox_pip-0.0.10.dist-info/top_level.txt
netbox_pip-0.0.10.dist-info/RECORD
